SuffixAutomaton.py
SuffixAutomaton-0.1.6.dist-info/METADATA
SuffixAutomaton-0.1.6.dist-info/WHEEL
SuffixAutomaton-0.1.6.dist-info/top_level.txt
SuffixAutomaton-0.1.6.dist-info/RECORD
