Metadata-Version: 2.1
Name: SuffixAutomaton
Version: 0.1.6
Summary: suffix automaton by words, to get text common substrings
Home-page: https://github.com/laohur/SuffixAutomaton
Author: laohur
Author-email: laohur@gmail.com
License: [Anti-996 License](https: // github.com/996icu/996.ICU/blob/master/LICENSE)
Keywords: Suffix Automaton,sam
Requires-Python: >=3.0
